ids_lib/__init__.py
ids_lib/core/__init__.py
ids_lib/data/__init__.py
ids_lib/enums/__init__.py
ids_lib/enums/scenarios.py
ids_lib/helpers/__init__.py
ids_lib/models/__init__.py
ids_lib-0.1.3.dev0.dist-info/LICENSE
ids_lib-0.1.3.dev0.dist-info/METADATA
ids_lib-0.1.3.dev0.dist-info/WHEEL
ids_lib-0.1.3.dev0.dist-info/top_level.txt
ids_lib-0.1.3.dev0.dist-info/RECORD
