Metadata-Version: 2.1
Name: ids-lib
Version: 0.1.3.dev0
Summary: Common functionality and preprocessing for intrusion detection
Home-page: UNKNOWN
Author: dnk0 <Dennis Kreußel>
Author-email: dnk0@protonmail.com
License: UNKNOWN
Platform: UNKNOWN
Classifier: License :: OSI Approved :: MIT License
Requires-Python: >=3.6
Requires-Dist: numpy (==1.17.0)
Requires-Dist: pandas (==0.25.1)
Requires-Dist: scikit-learn (==0.21.3)
Requires-Dist: scipy (==1.3.1)
Requires-Dist: nltk (==3.4.5)
Requires-Dist: matplotlib (==3.1.1)
Requires-Dist: torch (==1.2.0)
Requires-Dist: configparser (==3.8.1)
